vlight/__init__.py
vlight/validate.py
vlight-1.2.1.dist-info/METADATA
vlight-1.2.1.dist-info/RECORD
vlight-1.2.1.dist-info/WHEEL
vlight-1.2.1.dist-info/top_level.txt
