Metadata-Version: 2.1
Name: vlight
Version: 1.2.1
Summary: a simple package for validation data
Home-page: https://github.com/amirrezasalimi/vlight
Author: Amirreza salimi
Author-email: amirrezasalimi0@gmail.com
License: UNKNOWN
Platform: UNKNOWN
Classifier: Programming Language :: Python :: 3
Classifier: License :: OSI Approved :: MIT License
Classifier: Operating System :: OS Independent
